carconnectivity_abrp/__init__.py
carconnectivity_abrp/carconnectivity_abrp_base.py
carconnectivity_plugin_abrp-0.6.1.dist-info/licenses/LICENSE
carconnectivity_plugins/abrp/__init__.py
carconnectivity_plugins/abrp/_version.py
carconnectivity_plugins/abrp/abrp_object.py
carconnectivity_plugins/abrp/plugin.py
carconnectivity_plugins/abrp/ui/plugin_ui.py
carconnectivity_plugins/abrp/ui/templates/abrp/status.html
carconnectivity_plugin_abrp-0.6.1.dist-info/METADATA
carconnectivity_plugin_abrp-0.6.1.dist-info/WHEEL
carconnectivity_plugin_abrp-0.6.1.dist-info/entry_points.txt
carconnectivity_plugin_abrp-0.6.1.dist-info/top_level.txt
carconnectivity_plugin_abrp-0.6.1.dist-info/RECORD
