Metadata-Version: 2.4
Name: carconnectivity-plugin-abrp
Version: 0.6.1
Summary: CarConnectivity plugin for publishing data to ABRP (https://abetterrouteplanner.com)
Author: Till Steinbach
License: MIT License
Classifier: Development Status :: 3 - Alpha
Classifier: License :: OSI Approved :: MIT License
Classifier: Intended Audience :: End Users/Desktop
Classifier: Intended Audience :: System Administrators
Classifier: Programming Language :: Python :: 3.9
Classifier: Programming Language :: Python :: 3.10
Classifier: Programming Language :: Python :: 3.11
Classifier: Programming Language :: Python :: 3.12
Classifier: Programming Language :: Python :: 3.13
Classifier: Topic :: Utilities
Classifier: Topic :: System :: Monitoring
Classifier: Topic :: Home Automation
Requires-Python: >=3.9
License-File: LICENSE
Requires-Dist: carconnectivity>=0.7.1
Requires-Dist: requests~=2.32.3
Dynamic: license-file
